sientia_tracker/__init__.py
sientia_tracker/basic.py
sientia_tracker/regression.py
sientia_tracker/simple_tracker.py
sientia_tracker-1.0.7.dist-info/LICENCE
sientia_tracker-1.0.7.dist-info/METADATA
sientia_tracker-1.0.7.dist-info/WHEEL
sientia_tracker-1.0.7.dist-info/top_level.txt
sientia_tracker-1.0.7.dist-info/RECORD
