Metadata-Version: 2.1
Name: sientia_tracker
Version: 1.0.7
Summary: Library for Aignosi Tracking API
Author: ['Ítalo Azevedo', 'Pedro Bahia', 'Matheus Demoner']
Author-email: ['italo@aignosi.com.br', 'pedro.bahia@aignosi.com.br', 'matheus@aignosi.com.br']
License: Apache License 2.0
Keywords: sientia
Classifier: Programming Language :: Python :: 3
Classifier: License :: OSI Approved :: Apache Software License
Classifier: Operating System :: OS Independent
License-File: LICENCE
Requires-Dist: mlflow ==2.10.1
Requires-Dist: typing
